eth_predictor/__init__.py
eth_predictor/app.py
ethereum_predictor-1.0.1.dist-info/METADATA
ethereum_predictor-1.0.1.dist-info/WHEEL
ethereum_predictor-1.0.1.dist-info/entry_points.txt
ethereum_predictor-1.0.1.dist-info/top_level.txt
ethereum_predictor-1.0.1.dist-info/RECORD
