Metadata-Version: 2.1
Name: ethereum-predictor
Version: 1.0.1
Summary: Ethereum Price Prediction Tool
Author: Isaiah J Peterson
Author-email: isaiahjpeterson@gmail.com
Requires-Dist: ccxt
Requires-Dist: pandas
Requires-Dist: numpy
Requires-Dist: tensorflow
Requires-Dist: joblib
Requires-Dist: pandas-ta
